fastapi_cachette/__init__.py
fastapi_cachette/backends/__init__.py
fastapi_cachette/backends/dynamodb.py
fastapi_cachette/backends/inmemory.py
fastapi_cachette/backends/memcached.py
fastapi_cachette/backends/mongodb.py
fastapi_cachette/backends/redis.py
fastapi_cachette/cachette_config.py
fastapi_cachette/codecs/__init__.py
fastapi_cachette/codecs/dataframe/csv.py
fastapi_cachette/codecs/dataframe/feather.py
fastapi_cachette/codecs/dataframe/parquet.py
fastapi_cachette/codecs/json.py
fastapi_cachette/codecs/msgpack.py
fastapi_cachette/codecs/orjson.py
fastapi_cachette/codecs/pickle.py
fastapi_cachette/codecs/vanilla.py
fastapi_cachette/core.py
fastapi_cachette/load_config.py
fastapi_cachette-0.1.6.dist-info/LICENSE
fastapi_cachette-0.1.6.dist-info/METADATA
fastapi_cachette-0.1.6.dist-info/WHEEL
fastapi_cachette-0.1.6.dist-info/RECORD
